LICENSE
README.md
requirements.txt
setup.py
mcrit/SingleJobWorker.py
mcrit/SpawningWorker.py
mcrit/Worker.py
mcrit/__init__.py
mcrit/__main__.py
mcrit.egg-info/PKG-INFO
mcrit.egg-info/SOURCES.txt
mcrit.egg-info/dependency_links.txt
mcrit.egg-info/entry_points.txt
mcrit.egg-info/requires.txt
mcrit.egg-info/top_level.txt
mcrit/client/McritClient.py
mcrit/client/McritConsole.py
mcrit/client/__init__.py
mcrit/config/ConfigInterface.py
mcrit/config/GunicornConfig.py
mcrit/config/McritConfig.py
mcrit/config/MinHashConfig.py
mcrit/config/QueueConfig.py
mcrit/config/ShinglerConfig.py
mcrit/config/StorageConfig.py
mcrit/config/__init__.py
mcrit/index/MinHashIndex.py
mcrit/index/SearchCursor.py
mcrit/index/SearchQueryParser.py
mcrit/index/SearchQueryTree.py
mcrit/index/__init__.py
mcrit/libs/__init__.py
mcrit/libs/graph.py
mcrit/libs/mongoqueue.py
mcrit/libs/pymmh3.py
mcrit/libs/utility.py
mcrit/matchers/FunctionCfgMatcher.py
mcrit/matchers/MatcherCross.py
mcrit/matchers/MatcherFlags.py
mcrit/matchers/MatcherInterface.py
mcrit/matchers/MatcherQuery.py
mcrit/matchers/MatcherQueryFunction.py
mcrit/matchers/MatcherSample.py
mcrit/matchers/MatcherVs.py
mcrit/matchers/MatcherVsGroup.py
mcrit/matchers/__init__.py
mcrit/minhash/MinHash.py
mcrit/minhash/MinHasher.py
mcrit/minhash/ShingleLoader.py
mcrit/minhash/__init__.py
mcrit/queue/JobCollection.py
mcrit/queue/LocalQueue.py
mcrit/queue/QueueFactory.py
mcrit/queue/QueueRemoteCalls.py
mcrit/queue/__init__.py
mcrit/server/BlocksResource.py
mcrit/server/FamilyResource.py
mcrit/server/FunctionResource.py
mcrit/server/JobResource.py
mcrit/server/MatchResource.py
mcrit/server/QueryResource.py
mcrit/server/SampleResource.py
mcrit/server/StatusResource.py
mcrit/server/__init__.py
mcrit/server/application_routes.py
mcrit/server/utils.py
mcrit/server/wsgi.py
mcrit/storage/FamilyEntry.py
mcrit/storage/FunctionEntry.py
mcrit/storage/FunctionLabelEntry.py
mcrit/storage/MatchedFunctionEntry.py
mcrit/storage/MatchedSampleEntry.py
mcrit/storage/MatchingCache.py
mcrit/storage/MatchingResult.py
mcrit/storage/MemoryStorage.py
mcrit/storage/MongoDbStorage.py
mcrit/storage/SampleEntry.py
mcrit/storage/StorageFactory.py
