Metadata-Version: 2.1
Name: mcrit
Version: 1.4.3
Summary: MCRIT is a framework created for simplified application of the MinHash algorithm to code similarity.
Home-page: https://github.com/danielplohmann/mcrit
Author: Daniel Plohmann, Manuel Blatt, Steffen Enders, Paul Hordiienko
Author-email: daniel.plohmann@fkie.fraunhofer.de
License: NU General Public License v3 (GPLv3)
Classifier: Development Status :: 4 - Beta
Classifier: License :: OSI Approved :: GNU General Public License v3 (GPLv3)
Classifier: Operating System :: OS Independent
Classifier: Programming Language :: Python :: 3
Classifier: Topic :: Security
Classifier: Topic :: Scientific/Engineering :: Information Analysis
License-File: LICENSE
